odoo/addons/delivery_price_rule_untaxed/README.rst
odoo/addons/delivery_price_rule_untaxed/__init__.py
odoo/addons/delivery_price_rule_untaxed/__manifest__.py
odoo/addons/delivery_price_rule_untaxed/data/delivery_price_rule_untaxed_demo.xml
odoo/addons/delivery_price_rule_untaxed/i18n/delivery_price_rule_untaxed.pot
odoo/addons/delivery_price_rule_untaxed/i18n/fr.po
odoo/addons/delivery_price_rule_untaxed/i18n/it.po
odoo/addons/delivery_price_rule_untaxed/models/__init__.py
odoo/addons/delivery_price_rule_untaxed/models/delivery_carrier.py
odoo/addons/delivery_price_rule_untaxed/models/delivery_price_rule.py
odoo/addons/delivery_price_rule_untaxed/readme/CONTRIBUTORS.rst
odoo/addons/delivery_price_rule_untaxed/readme/DESCRIPTION.rst
odoo/addons/delivery_price_rule_untaxed/static/description/icon.png
odoo/addons/delivery_price_rule_untaxed/static/description/index.html
odoo/addons/delivery_price_rule_untaxed/tests/__init__.py
odoo/addons/delivery_price_rule_untaxed/tests/test_delivery_price_rule_untaxed.py
odoo12_addon_delivery_price_rule_untaxed-12.0.1.0.2.dist-info/METADATA
odoo12_addon_delivery_price_rule_untaxed-12.0.1.0.2.dist-info/WHEEL
odoo12_addon_delivery_price_rule_untaxed-12.0.1.0.2.dist-info/top_level.txt
odoo12_addon_delivery_price_rule_untaxed-12.0.1.0.2.dist-info/RECORD
