Metadata-Version: 2.1
Name: odoo12-addon-delivery-price-rule-untaxed
Version: 12.0.1.0.2
Summary: Add untaxed amount to variables for price delivery price rule
Home-page: https://github.com/OCA/delivery-carrier
Author: Agile Business Group, Odoo Community Association (OCA)
Author-email: support@odoo-community.org
License: AGPL-3
Platform: UNKNOWN
Classifier: Programming Language :: Python
Classifier: Framework :: Odoo
Classifier: Framework :: Odoo :: 12.0
Classifier: License :: OSI Approved :: GNU Affero General Public License v3
Classifier: Development Status :: 4 - Beta
Requires-Python: >=3.5
Requires-Dist: odoo (<12.1dev,>=12.0a)
